hamster_dbus/__init__.py
hamster_dbus/hamster_dbus_service.py
hamster_dbus/helpers.py
hamster_dbus/objects.py
hamster_dbus/storage.py
hamster_dbus-0.10.0.dist-info/DESCRIPTION.rst
hamster_dbus-0.10.0.dist-info/METADATA
hamster_dbus-0.10.0.dist-info/RECORD
hamster_dbus-0.10.0.dist-info/WHEEL
hamster_dbus-0.10.0.dist-info/entry_points.txt
hamster_dbus-0.10.0.dist-info/metadata.json
hamster_dbus-0.10.0.dist-info/top_level.txt
