Metadata-Version: 2.0
Name: hamster-dbus
Version: 0.10.0
Summary: A dbus interface to hamster-lib.
Home-page: https://github.com/elbenfreund/hamster-dbus
Author: Eric Goller
Author-email: eric.goller@ninjaduck.solutions
License: GPL3
Keywords: hamster-dbus
Platform: UNKNOWN
Classifier: Development Status :: 2 - Pre-Alpha
Classifier: Intended Audience :: Developers
Classifier: License :: OSI Approved :: GNU General Public License v3 (GPLv3)
Classifier: Natural Language :: English
Classifier: Programming Language :: Python :: 2
Classifier: Programming Language :: Python :: 2.7
Classifier: Programming Language :: Python :: 3
Classifier: Programming Language :: Python :: 3.4
Requires-Dist: future
Requires-Dist: hamster-lib
